bar_chooser
