Metadata-Version: 1.0
Name: bar-chooser
Version: 0.1.3
Summary: Script that help you to choose a bar to drink with someone.
Home-page: https://github.com/strizhechenko/bar-chooser
Author: Oleg Strizhechenko
Author-email: oleg.strizhechenko@gmail.com
License: MIT
Platform: UNKNOWN
